MANIFEST.in
README.md
setup.py
django_paymill.egg-info/PKG-INFO
django_paymill.egg-info/SOURCES.txt
django_paymill.egg-info/dependency_links.txt
django_paymill.egg-info/requires.txt
django_paymill.egg-info/top_level.txt
paymill/__init__.py
paymill/admin.py
paymill/apps.py
paymill/forms.py
paymill/signals.py
paymill/urls.py
paymill/views.py
paymill/webhooks.py
paymill/management/__init__.py
paymill/management/commands/__init__.py
paymill/management/commands/update_from_paymill.py
paymill/models/__init__.py
paymill/models/base.py
paymill/models/choices.py
paymill/models/client.py
paymill/models/offer.py
paymill/models/payment.py
paymill/models/subscription.py
paymill/models/transaction.py
paymill/templatetags/__init__.py
paymill/templatetags/paymill.py