Metadata-Version: 1.1
Name: django-paymill
Version: 0.1.1
Summary: django-paymill is a django app for easily integrating Paymill as a payment gateway for django projects.
Home-page: https://github.com/ulfur/django-paymill
Author: Úlfur Kristjánsson
Author-email: ulfurk@ulfurk.com
License: UNKNOWN
Platform: UNKNOWN
Classifier: Development Status :: 4 - Beta
Classifier: Environment :: Web Environment
Classifier: Intended Audience :: Developers
Classifier: Operating System :: OS Independent
Classifier: Programming Language :: Python
